wb_fun_logger-1.2.3.dist-info/licenses/LICENSE
webhook_logger/__init__.py
webhook_logger/config.py
webhook_logger/function_logger.py
webhook_logger/schemas/__init__.py
webhook_logger/utils/__init__.py
webhook_logger/utils/config_loader.py
webhook_logger/utils/create_webhook_data.py
wb_fun_logger-1.2.3.dist-info/METADATA
wb_fun_logger-1.2.3.dist-info/WHEEL
wb_fun_logger-1.2.3.dist-info/top_level.txt
wb_fun_logger-1.2.3.dist-info/RECORD
